extrucal/__init__.py
extrucal/cable_extrusion.py
extrucal/extrusion.py
extrucal/rod_extrusion.py
extrucal/sheet_extrusion.py
extrucal/tube_extrusion.py
extrucal-1.4.21.dist-info/LICENSE
extrucal-1.4.21.dist-info/METADATA
extrucal-1.4.21.dist-info/WHEEL
extrucal-1.4.21.dist-info/RECORD
