Metadata-Version: 2.1
Name: extrucal
Version: 1.4.21
Summary: Provides functions for calculating various parameters in extrusion processes
Home-page: https://github.com/johnwslee/extrucal
License: MIT
Author: John W.S. Lee
Requires-Python: >=3.9,<4.0
Classifier: License :: OSI Approved :: MIT License
Classifier: Programming Language :: Python :: 3
Classifier: Programming Language :: Python :: 3.9
Classifier: Programming Language :: Python :: 3.10
Classifier: Programming Language :: Python :: 3.11
Requires-Dist: altair-saver (>=0.5.0,<0.6.0)
Requires-Dist: codecov (==2.1.13)
Requires-Dist: ipykernel (>=6.9.1,<7.0.0)
Requires-Dist: numpy (>=1.22.2,<2.0.0)
Requires-Dist: pandas (>=1.4.1,<2.0.0)
Requires-Dist: plotly (==5.9.0)
Requires-Dist: sphinx-autoapi (>=1.8.4,<2.0.0)
Requires-Dist: sphinx-rtd-theme (>=1.0.0,<2.0.0)
Project-URL: Documentation, https://extrucal.readthedocs.io/en/latest/
Project-URL: Repository, https://github.com/johnwslee/extrucal
